mfrc522/BasicMFRC522.py
mfrc522/MFRC522.py
mfrc522/SimpleMFRC522.py
mfrc522/__init__.py
mfrc522_python-0.0.7.dist-info/LICENSE
mfrc522_python-0.0.7.dist-info/METADATA
mfrc522_python-0.0.7.dist-info/WHEEL
mfrc522_python-0.0.7.dist-info/top_level.txt
mfrc522_python-0.0.7.dist-info/RECORD
