Metadata-Version: 2.1
Name: mfrc522-python
Version: 0.0.7
Summary: The mfrc522-python library is used to interact with RFID readers that use the MFRC522 chip interfaced with a Raspberry Pi.
Author: Aditya
Project-URL: Homepage, https://github.com/1AdityaX/mfrc522-python
Project-URL: Bug Tracker, https://github.com/1AdityaX/mfrc522-python/issues
Classifier: Programming Language :: Python :: 3
Classifier: License :: OSI Approved :: GNU General Public License v3 (GPLv3)
Classifier: Operating System :: POSIX :: Linux
Requires-Python: >=3.7
License-File: LICENSE
